finn_examples/__init__.py
finn_examples/driver.py
finn_examples/models.py
finn_examples/bitfiles/__init__.py
finn_examples/bitfiles/bitfiles.zip.link
finn_examples/notebooks/0_mnist_with_fc_networks.ipynb
finn_examples/notebooks/1_cifar10_with_cnv_networks.ipynb
finn_examples/notebooks/2_imagenet_with_mobilenet_v1.ipynb
finn_examples-0.0.2b0.dist-info/AUTHORS.rst
finn_examples-0.0.2b0.dist-info/LICENSE
finn_examples-0.0.2b0.dist-info/METADATA
finn_examples-0.0.2b0.dist-info/WHEEL
finn_examples-0.0.2b0.dist-info/entry_points.txt
finn_examples-0.0.2b0.dist-info/top_level.txt
finn_examples-0.0.2b0.dist-info/RECORD
