Metadata-Version: 2.1
Name: finn-examples
Version: 0.0.2b0
Summary: FINN Examples on PYNQ for Zynq and Alveo
Home-page: https://github.com/Xilinx/finn-examples
Author: Yaman Umuroglu
Author-email: yamanu@xilinx.com
License: Apache License 2.0
Download-URL: https://github.com/Xilinx/finn-examples
Platform: UNKNOWN
Requires-Python: >=3.5.2
License-File: LICENSE
License-File: AUTHORS.rst
Requires-Dist: pynq (>=2.5.1)
Requires-Dist: finn-base (==0.0.2b0)
Requires-Dist: finn-dataset-loading (==0.0.5)
Requires-Dist: matplotlib (<3.1) ; python_version<"3.6"
Requires-Dist: ipython (==7.9) ; python_version<"3.6"
Requires-Dist: matplotlib ; python_version>="3.6"
